Workbook

Sheet 📋 Materials Checklist
A1: 🍄 KABUTECH HIYAS — COMPLETE MATERIALS & PROCUREMENT CHECKLIST
A2: Precision Mushroom Grow House Automation | Target Budget: ₱15,000 PHP | 68 Components | High-Quality Digital Sensors
A3: 💡 INSTRUCTIONS: Update 'Status' dropdown (To Buy / Ordered / Received / In Stock) as you purchase items. Enter your 'Actual Spent (₱)' to track budget in real-time.
A4: Status | B4: Code | C4: Component Name | D4: Category | E4: Technical Specifications & Rationale | F4: Qty | G4: Unit | H4: Min Est (₱) | I4: Max Est (₱) | J4: Min Total (₱) | K4: Max Total (₱) | L4: Actual Spent (₱) | M4: Recommended Vendor / Store | N4: Search Keywords / Model | O4: Procurement & Assembly Notes
A5: 🔬 CATEGORY A: SENSORS & PROBE ELECTRONICS (QUALITY-GRADE)
A6: To Buy | B6: A1 | C6: SHT31-D Temperature & Humidity Module | D6: Sensors & Probe Electronics | E6: ±2% RH, ±0.3°C accuracy. Digital I2C bus. Factory calibrated. Superior to DHT11. | F6: 1 | G6: pc | H6: 120 | I6: 180 | J6: =F6*H6 | K6: =F6*I6 | M6: Shopee / Lazada / Makerlab PH | N6: SHT31-D sensor module I2C | O6: Essential for high-humidity mushroom chamber.
A7: To Buy | B7: A2 | C7: BH1750 Digital Light Sensor (GY-302) | D7: Sensors & Probe Electronics | E7: 1–65535 lux, 16-bit resolution, direct lux output, I2C. Replaces unreliable LDR. | F7: 1 | G7: pc | H7: 80 | I7: 150 | J7: =F7*H7 | K7: =F7*I7 | M7: Shopee / Lazada / Circuit Rocks | N7: BH1750 GY-302 light sensor module | O7: Mount facing grow bags to track pinhead lighting.
A8: To Buy | B8: A3 | C8: SCD41 True NDIR CO₂ Sensor Module | D8: Sensors & Probe Electronics | E8: Photoacoustic NDIR, 400–5000 ppm, ±(40 ppm + 5%), I2C. True CO₂ measurement. | F8: 1 | G8: pc | H8: 1800 | I8: 2500 | J8: =F8*H8 | K8: =F8*I8 | M8: Shopee PH / AliExpress | N8: Sensirion SCD41 CO2 sensor module | O8: Most critical sensor for thesis credibility. Not MQ-135.
A9: To Buy | B9: A4 | C9: Capacitive Water Level Sensor (XKC-Y25-T12V) | D9: Sensors & Probe Electronics | E9: Non-contact liquid level, penetrates 20mm plastic wall, 5-24V DC, digital out. | F9: 1 | G9: pc | H9: 250 | I9: 400 | J9: =F9*H9 | K9: =F9*I9 | M9: Shopee / Lazada / Makerlab PH | N9: XKC-Y25-T12V non contact water level | O9: Outside reservoir mounting. No corrosion or electrolysis.
A10: To Buy | B10: A5 | C10: YF-S201 Water Flow Sensor (Hall Effect) | D10: Sensors & Probe Electronics | E10: 1–30 L/min range, working pressure <1.75MPa, pulse output, food-grade nylon. | F10: 1 | G10: pc | H10: 150 | I10: 220 | J10: =F10*H10 | K10: =F10*I10 | M10: Shopee / Lazada | N10: YF-S201 water flow sensor 1/2 inch | O10: Monitors mist delivery & alerts if reservoir runs dry.
A11: To Buy | B11: A6 | C11: 0.96" SSD1306 OLED Display (I2C) | D11: Sensors & Probe Electronics | E11: 128×64 resolution, monochrome white/blue, I2C address 0x3C, 3.3V/5V compatible. | F11: 1 | G11: pc | H11: 100 | I11: 150 | J11: =F11*H11 | K11: =F11*I11 | M11: Shopee / Lazada / Makerlab PH | N11: 0.96 inch I2C OLED display SSD1306 | O11: Cabinet face display for live readings and IP/WiFi.
A12: To Buy | B12: A7 | C12: Perfboard / Prototype PCB (5×7cm) | D12: Sensors & Probe Electronics | E12: FR-4 double-sided prototype board with plated through-holes, 2.54mm pitch. | F12: 2 | G12: pcs | H12: 25 | I12: 50 | J12: =F12*H12 | K12: =F12*I12 | M12: Shopee / Electronics Store | N12: 5x7cm double sided prototype PCB FR4 | O12: For mounting SHT31 + BH1750 + SCD41 inside probe.
A13: Subtotal — Category A (Sensors & Probe Electronics): | J13: =SUM(J6:J12) | K13: =SUM(K6:K12) | L13: =SUM(L6:L12)
A14: 🏠 CATEGORY B: HANGING SENSOR PROBE HOUSING (PVC BELL REDUCER DESIGN)
A15: To Buy | B15: B1 | C15: 2" to 1" PVC Bell Reducer (White/Gray) | D15: Hanging Sensor Probe Housing | E15: Schedule 40 PVC fitting. 2" bell opening down to 1" neck. Lightweight housing. | F15: 1 | G15: pc | H15: 25 | I15: 45 | J15: =F15*H15 | K15: =F15*I15 | M15: Local Hardware (Citi / Wilcon / Ace) | N15: 2 x 1 PVC bell reducer fitting | O15: Forms inverted bell chamber shielding sensors from mist.
A16: To Buy | B16: B2 | C16: M16 or M20 IP68 Waterproof Cable Gland | D16: Hanging Sensor Probe Housing | E16: Nylon PA66 body, rubber clamping ring, IP68 rated, fits cables 4-8mm / 6-12mm. | F16: 1 | G16: pc | H16: 30 | I16: 60 | J16: =F16*H16 | K16: =F16*I16 | M16: Shopee / Lazada / Hardware | N16: M16 or M20 cable gland IP68 waterproof | O16: Screws into top neck; clamps cable and hangs probe.
A17: To Buy | B17: B3 | C17: PG7 Cable Gland (Nylon, IP68) | D17: Hanging Sensor Probe Housing | E17: Mini cable gland for 3-6.5mm cables, weatherproof sealing. | F17: 2 | G17: pcs | H17: 15 | I17: 25 | J17: =F17*H17 | K17: =F17*I17 | M17: Shopee / Hardware Store | N17: PG7 cable gland nylon IP68 | O17: Internal cable strain relief and wire pass-throughs.
A18: To Buy | B18: B4 | C18: Fine Stainless Steel Mesh / Nylon Filter | D18: Hanging Sensor Probe Housing | E18: 80-120 mesh SS304 wire cloth or dense nylon micron mesh. | F18: 1 | G18: sheet | H18: 30 | I18: 60 | J18: =F18*H18 | K18: =F18*I18 | M18: Hardware Store / Shopee | N18: Stainless steel 304 mesh screen 100 mesh | O18: Glued to 2" bottom rim. Stops droplets, passes CO2.
A19: To Buy | B19: B5 | C19: PTFE Hydrophobic Membrane Disc (13-25mm) | D19: Hanging Sensor Probe Housing | E19: ePTFE breathable membrane, hydrophobic IP67 rating, gas permeable. | F19: 1 | G19: pc | H19: 40 | I19: 80 | J19: =F19*H19 | K19: =F19*I19 | M19: Shopee | N19: PTFE membrane disc sensor waterproof | O19: Glued over SCD41 aperture to prevent condensation.
A20: To Buy | B20: B6 | C20: PVC Solvent Cement & Rapid Epoxy | D20: Hanging Sensor Probe Housing | E20: 100ml PVC cement + 2-part rapid epoxy (Pioneer/Devcon). | F20: 1 | G20: tube | H20: 45 | I20: 80 | J20: =F20*H20 | K20: =F20*I20 | M20: Any Hardware Store | N20: PVC cement Neltex + Pioneer epoxy | O20: Bonds screen to PVC rim and seals gland threads.
A21: To Buy | B21: B7 | C21: Printed Vinyl Label Sticker | D21: Hanging Sensor Probe Housing | E21: Weatherproof vinyl sticker: 'KABUTECH HIYAS — Probe SN-01'. | F21: 1 | G21: pc | H21: 20 | I21: 30 | J21: =F21*H21 | K21: =F21*I21 | M21: Print Shop / DIY Vinyl | N21: Waterproof vinyl sticker printing | O21: Professional thesis branding for probe assembly.
A22: To Buy | B22: B8 | C22: Nylon Cable Zip Ties (100mm) | D22: Hanging Sensor Probe Housing | E22: 2.5mm × 100mm black nylon UV-resistant zip ties (Pack of 100). | F22: 1 | G22: pack | H22: 30 | I22: 45 | J22: =F22*H22 | K22: =F22*I22 | M22: Hardware Store / Shopee | N22: Nylon zip ties 100mm black pack | O22: Internal wire bundling and strain relief.
A23: Subtotal — Category B (Hanging Sensor Probe Housing): | J23: =SUM(J15:J22) | K23: =SUM(K15:K22) | L23: =SUM(L15:L22)
A24: 🧠 CATEGORY C: CONTROLLER BOARD & CORE ELECTRONICS
A25: To Buy | B25: C1 | C25: ESP32-S3 DevKit N16R8 (USB-C) | D25: Controller Board & Core Electronics | E25: 16MB Flash, 8MB PSRAM, 240MHz Dual Core, WiFi 4 + BLE 5.0. Dual USB-C. | F25: 1 | G25: pc | H25: 350 | I25: 500 | J25: =F25*H25 | K25: =F25*I25 | M25: Shopee / Makerlab PH / Circuit Rocks | N25: ESP32-S3 N16R8 DevKit USB-C | O25: Verify 'N16R8' in listing for full memory & speed.
A26: To Buy | B26: C2 | C26: 8-Channel Relay Module (5V, Optocoupled) | D26: Controller Board & Core Electronics | E26: 8-ch optoisolated relay board, active LOW trigger, 10A 250VAC rating. | F26: 1 | G26: pc | H26: 180 | I26: 280 | J26: =F26*H26 | K26: =F26*I26 | M26: Shopee / Lazada / Makerlab PH | N26: 8 channel relay module 5V optocoupler | O26: Controls: Exhaust, Intake, Mister, Light, Solenoid + 3 spares.
A27: To Buy | B27: C3 | C27: Logic Level Shifter (3.3V ↔ 5V, 4-Ch) | D27: Controller Board & Core Electronics | E27: Bi-directional I2C / digital logic level converter with BSS138 MOSFETs. | F27: 1 | G27: pc | H27: 30 | I27: 50 | J27: =F27*H27 | K27: =F27*I27 | M27: Shopee / Lazada | N27: 4 channel logic level converter 3.3V 5V | O27: Protects ESP32 3.3V GPIOs driving 5V relay inputs.
A28: To Buy | B28: C4 | C28: Mini Breadboard / Expansion Strips | D28: Controller Board & Core Electronics | E28: 170-tie point mini solderless breadboard with adhesive backing. | F28: 2 | G28: pcs | H28: 25 | I28: 40 | J28: =F28*H28 | K28: =F28*I28 | M28: Shopee / Electronics Store | N28: 170 tie point mini breadboard | O28: Prototyping power rail distribution inside cabinet.
A29: To Buy | B29: C5 | C29: LM2596 DC-DC Step-Down Buck Converter | D29: Controller Board & Core Electronics | E29: Input 4-40V, Output 1.25-35V adjustable, 3A peak, high efficiency. | F29: 1 | G29: pc | H29: 40 | I29: 70 | J29: =F29*H29 | K29: =F29*I29 | M29: Shopee / Lazada | N29: LM2596 DC-DC buck converter module | O29: Steps down 12V rail to clean 5.0V for MCU & relays.
A30: To Buy | B30: C6 | C30: 5V 1A Voltage Regulator Module (AMS1117) | D30: Controller Board & Core Electronics | E30: Linear regulator module with input/output filter capacitors & power LED. | F30: 1 | G30: pc | H30: 20 | I30: 40 | J30: =F30*H30 | K30: =F30*I30 | M30: Shopee / Electronics Store | N30: AMS1117 5V power supply module | O30: Dedicated filtered 5V rail to prevent relay-induced brownouts.
A31: To Buy | B31: C7 | C31: 3-Position Toggle Switch (Auto/Off/Manual) | D31: Controller Board & Core Electronics | E31: Panel-mount 3-position (ON-OFF-ON) heavy-duty toggle switch. | F31: 1 | G31: pc | H31: 30 | I31: 50 | J31: =F31*H31 | K31: =F31*I31 | M31: Shopee / Hardware Store | N31: Toggle switch 3 position ON-OFF-ON panel mount | O31: Hardware override switch: Auto PID / Off / Manual Mode.
A32: To Buy | B32: C8 | C32: 5mm LEDs (R, G, B, Y) + 220Ω Resistors | D32: Controller Board & Core Electronics | E32: Panel-mount 5mm LEDs with bezels + 1/4W 220Ω current limiting resistors. | F32: 1 | G32: set | H32: 30 | I32: 40 | J32: =F32*H32 | K32: =F32*I32 | M32: Shopee / Electronics Store | N32: 5mm LED with bezel panel mount set | O32: Front panel indicators: Power (G), WiFi (B), Alarm (R), Mode (Y).
A33: To Buy | B33: C9 | C33: Momentary Push Button (12mm, Panel-Mount) | D33: Controller Board & Core Electronics | E33: Waterproof momentary push button, normally open (NO), flush metal head. | F33: 1 | G33: pc | H33: 15 | I33: 30 | J33: =F33*H33 | K33: =F33*I33 | M33: Shopee / Electronics Store | N33: 12mm waterproof momentary push button metal | O33: External Cabinet System Reset / WiFi Provision button.
A34: To Buy | B34: C10 | C34: 10kΩ 1/4W Resistors (Pack of 20) | D34: Controller Board & Core Electronics | E34: 1% tolerance 1/4W metal film through-hole resistors. | F34: 1 | G34: pack | H34: 20 | I34: 30 | J34: =F34*H34 | K34: =F34*I34 | M34: Shopee / Electronics Store | N34: 10k ohm 1/4W metal film resistors pack | O34: I2C pull-ups, button debouncing, switch logic.
A35: To Buy | B35: C11 | C35: 1N4007 Rectifier Diodes (Pack of 10) | D35: Controller Board & Core Electronics | E35: 1000V 1A standard recovery rectifier diode, DO-41 package. | F35: 1 | G35: pack | H35: 15 | I35: 30 | J35: =F35*H35 | K35: =F35*I35 | M35: Shopee / Electronics Store | N35: 1N4007 diode pack 10pcs | O35: Flyback diode protection across pump, solenoid & fan coils.
A36: To Buy | B36: C12 | C36: Inline Blade Fuse Holder (16AWG) + 5A Fuses | D36: Controller Board & Core Electronics | E36: Waterproof automotive inline fuse holder + 5A blade fuses (Pack of 5). | F36: 2 | G36: pcs | H36: 25 | I36: 50 | J36: =F36*H36 | K36: =F36*I36 | M36: Shopee / Automotive Store | N36: Inline blade fuse holder waterproof 16AWG | O36: Protects main 12V rail and high-draw actuator branches.
A37: Subtotal — Category C (Controller Board & Core Electronics): | J37: =SUM(J25:J36) | K37: =SUM(K25:K36) | L37: =SUM(L25:L36)
A38: ⚡ CATEGORY D: POWER SUPPLY & DISTRIBUTION
A39: To Buy | B39: D1 | C39: 12V 5A (60W) Enclosed Switching PSU | D39: Power Supply & Distribution | E39: Metal mesh chassis, universal AC in (110-240V), regulated 12VDC ±1%. | F39: 1 | G39: pc | H39: 600 | I39: 1000 | J39: =F39*H39 | K39: =F39*I39 | M39: Shopee / Lazada / Alexan | N39: 12V 5A switching power supply metal case | O39: Powers entire system safely: ESP32, fans, pump, valve.
A40: To Buy | B40: D2 | C40: IEC C14 Inlet Socket with Fuse & Switch | D40: Power Supply & Distribution | E40: Panel-mount AC socket with built-in 5x20mm fuse drawer & illuminated switch. | F40: 1 | G40: pc | H40: 60 | I40: 100 | J40: =F40*H40 | K40: =F40*I40 | M40: Shopee / Lazada / Alexan | N40: IEC C14 power socket with fuse switch panel mount | O40: Professional computer kettle cord inlet on enclosure face.
A41: To Buy | B41: D3 | C41: 220V AC Power Cord (3-Prong PH, 1.5m) | D41: Power Supply & Distribution | E41: Heavy-duty 3-conductor (G, N, L) cable, rated 250V 10A, molded C13 plug. | F41: 1 | G41: pc | H41: 80 | I41: 150 | J41: =F41*H41 | K41: =F41*I41 | M41: Hardware Store / Shopee | N41: PC power cord 3 prong IEC C13 1.5m | O41: Standard wall plug with true safety earth grounding.
A42: To Buy | B42: D4 | C42: 12-Position Terminal Block Strip (15A) | D42: Power Supply & Distribution | E42: Dual-row screw terminal strip with clear cover, 15A 600V rated. | F42: 2 | G42: pcs | H42: 30 | I42: 60 | J42: =F42*H42 | K42: =F42*I42 | M42: Shopee / Hardware Store | N42: TB-1512 barrier terminal block 12 position 15A | O42: Organized 12V (+), GND (-), and relay output distribution.
A43: To Buy | B43: D5 | C43: Wago 221 Lever Connectors (3-Wire, 5-Pack) | D43: Power Supply & Distribution | E43: Tool-free lever wire connectors, supports 24-12 AWG solid & stranded. | F43: 2 | G43: packs | H43: 50 | I43: 80 | J43: =F43*H43 | K43: =F43*I43 | M43: Shopee / Lazada | N43: Wago 221-413 3 wire lever connector | O43: Safe, reusable vibration-proof wire splicing inside box.
A44: To Buy | B44: D6 | C44: KCD1 Rocker Switch (ON-OFF, 220V 6A) | D44: Power Supply & Distribution | E44: Snap-in SPST rocker switch with red neon indicator, 19×13mm cutout. | F44: 1 | G44: pc | H44: 25 | I44: 40 | J44: =F44*H44 | K44: =F44*I44 | M44: Shopee / Hardware Store | N44: KCD1 rocker switch illuminated red 3 pin | O44: Master power switch on controller enclosure exterior.
A45: To Buy | B45: D7 | C45: Metal Oxide Varistor MOV (275V, 10D431K) | D45: Power Supply & Distribution | E45: 275VAC RMS surge suppressor, absorbs grid spikes & brownout transients. | F45: 1 | G45: pc | H45: 25 | I45: 30 | J45: =F45*H45 | K45: =F45*I45 | M45: Shopee / Electronics Store | N45: Varistor 10D431K 275V surge protector | O45: Wired across AC Live & Neutral at inlet for surge protection.
A46: Subtotal — Category D (Power Supply & Distribution): | J46: =SUM(J39:J45) | K46: =SUM(K39:K45) | L46: =SUM(L39:L45)
A47: 🔌 CATEGORY E: CONNECTORS & WIRING
A48: To Buy | B48: E1 | C48: GX16 4-Pin Aviation Connectors (M+F Sets) | D48: Connectors & Wiring | E48: 16mm metal chassis socket + cable plug, screw-locking, 5A rated. | F48: 6 | G48: sets | H48: 50 | I48: 100 | J48: =F48*H48 | K48: =F48*I48 | M48: Shopee / Lazada | N48: GX16 4 pin aviation connector male female | O48: Detachable ports: Exhaust, Intake, Mister, Light, Probe, Flow.
A49: To Buy | B49: E2 | C49: 4-Core Shielded Cable (22AWG, 3 Meters) | D49: Connectors & Wiring | E49: 4 stranded copper cores + aluminum foil shield + drain wire, flexible PVC. | F49: 1 | G49: roll (3m) | H49: 100 | I49: 180 | J49: =F49*H49 | K49: =F49*I49 | M49: Shopee / Lazada | N49: 4 core shielded cable 22AWG signal wire | O49: Controller to probe umbilical. Shielding stops I2C noise.
A50: To Buy | B50: E3 | C50: 18 AWG Silicone Stranded Wire (Red + Black) | D50: Connectors & Wiring | E50: High-temp (200°C) flexible tinned copper silicone wire (5m red, 5m black). | F50: 2 | G50: rolls | H50: 40 | I50: 60 | J50: =F50*H50 | K50: =F50*I50 | M50: Shopee / Lazada | N50: 18 AWG silicone wire red black 5m | O50: Main 12V high-current distribution inside cabinet.
A51: To Buy | B51: E4 | C51: 22 AWG Hookup Wire Assorted (6 Colors, 5m) | D51: Connectors & Wiring | E51: PVC insulated tinned copper wire in 6 distinct colors. | F51: 1 | G51: set | H51: 60 | I51: 100 | J51: =F51*H51 | K51: =F51*I51 | M51: Shopee / Electronics Store | N51: 22 AWG hookup wire kit assorted colors | O51: Internal signal wiring: ESP32 to shifters, display, LEDs.
A52: To Buy | B52: E5 | C52: Dupont Jumper Wires (40-Pin, 20cm, Assorted) | D52: Connectors & Wiring | E52: Multicolored breadboard jumpers (M-M, M-F, F-F). | F52: 3 | G52: sets | H52: 30 | I52: 50 | J52: =F52*H52 | K52: =F52*I52 | M52: Shopee / Lazada | N52: Dupont wire 20cm 40 pin M-M M-F F-F | O52: Bench prototyping and test jumpers.
A53: To Buy | B53: E6 | C53: IP68 Nylon Cable Glands (PG9 / PG11) | D53: Connectors & Wiring | E53: Weatherproof cable entry glands with rubber sealing washers & locknuts. | F53: 6 | G53: pcs | H53: 15 | I53: 30 | J53: =F53*H53 | K53: =F53*I53 | M53: Shopee / Hardware Store | N53: PG9 PG11 cable gland IP68 nylon | O53: Watertight cable pass-throughs into enclosure.
A54: To Buy | B54: E7 | C54: Heat Shrink Tubing Kit (120+ pcs Assorted) | D54: Connectors & Wiring | E54: Polyolefin 2:1 shrink tubing in assorted diameters (1.5mm-10mm). | F54: 1 | G54: kit | H54: 60 | I54: 100 | J54: =F54*H54 | K54: =F54*I54 | M54: Shopee / Lazada | N54: Heat shrink tubing kit assorted sizes | O54: Insulates aviation pins, splice joints, and LED legs.
A55: To Buy | B55: E8 | C55: JST-XH 2.54mm Connector Kit (2P, 3P, 4P) | D55: Connectors & Wiring | E55: Male PCB headers + female crimp housings + pins in organizer box. | F55: 1 | G55: kit | H55: 50 | I55: 80 | J55: =F55*H55 | K55: =F55*I55 | M55: Shopee / Lazada | N55: JST-XH 2.54mm connector kit with crimp pins | O55: Modular disconnects for sensors & display modules.
A56: To Buy | B56: E9 | C56: 40-Pin 2.54mm Female Header Strips | D56: Connectors & Wiring | E56: Gold-plated through-hole female socket strips. | F56: 2 | G56: pcs | H56: 15 | I56: 20 | J56: =F56*H56 | K56: =F56*I56 | M56: Shopee / Electronics Store | N56: 40 pin 2.54mm female header socket strip | O56: Sockets for ESP32 DevKit so MCU is pluggable/swappable.
A57: To Buy | B57: E10 | C57: Rosin Core Solder Wire (60/40, 0.8mm, 50g) | D57: Connectors & Wiring | E57: High purity 60% tin / 40% lead with 2.2% rosin flux core. | F57: 1 | G57: roll | H57: 50 | I57: 80 | J57: =F57*H57 | K57: =F57*I57 | M57: Shopee / Hardware Store | N57: Solder wire 60/40 0.8mm rosin core 50g | O57: Permanent soldering of boards, diodes, and aviation plugs.
A58: Subtotal — Category E (Connectors & Wiring): | J58: =SUM(J48:J57) | K58: =SUM(K48:K57) | L58: =SUM(L48:L57)
A59: 🌀 CATEGORY F: ACTUATORS (THE THINGS BEING CONTROLLED)
A60: To Buy | B60: F1 | C60: 12V DC Exhaust Fan (120mm / 4-Inch) | D60: Actuators | E60: 120×120×25mm, 12V DC, ball bearing, moisture-resistant, >70 CFM. | F60: 1 | G60: pc | H60: 180 | I60: 400 | J60: =F60*H60 | K60: =F60*I60 | M60: Shopee / Lazada | N60: 12V 120mm cooling fan ball bearing high airflow | O60: Extracts stale CO2 and heat from grow room ceiling.
A61: To Buy | B61: F2 | C61: 12V DC Circulation / Intake Fan (80-120mm) | D61: Actuators | E61: 12V DC, brushless, 0.2A, low noise with finger protection grill. | F61: 1 | G61: pc | H61: 130 | I61: 300 | J61: =F61*H61 | K61: =F61*I61 | M61: Shopee / Lazada | N61: 12V DC brushless fan 80mm or 120mm with grill | O61: Draws in fresh filtered air & circulates humidity.
A62: To Buy | B62: F3 | C62: 12V DC High-Pressure Misting Pump (60W) | D62: Actuators | E62: Self-priming diaphragm pump, 4-5 L/min, 0.8 MPa (115 PSI), auto pressure switch. | F62: 1 | G62: pc | H62: 350 | I62: 800 | J62: =F62*H62 | K62: =F62*I62 | M62: Shopee / Lazada | N62: 12V diaphragm pump misting 60W high pressure | O62: Atomizes water into ultra-fine fog without wetting beds.
A63: To Buy | B63: F4 | C63: Brass Misting Nozzles (0.3mm Orifice) | D63: Actuators | E63: Solid brass with stainless orifice, anti-drip spring, 20-70 bar rating. | F63: 5 | G63: pcs | H63: 15 | I63: 30 | J63: =F63*H63 | K63: =F63*I63 | M63: Shopee / Lazada / Hardware | N63: 0.3mm brass misting nozzle anti drip | O63: Overhead spray nozzles creating 15-30 micron fog.
A64: To Buy | B64: F5 | C64: Misting Tubing Kit (6mm PE Tubing 5m + Tees) | D64: Actuators | E64: 5m 1/4" (6mm) PE tubing + 5 slip-lock tee fittings + 1 end plug. | F64: 1 | G64: kit | H64: 150 | I64: 350 | J64: =F64*H64 | K64: =F64*I64 | M64: Shopee / Lazada | N64: Misting system kit 6mm PE pipe slip lock fittings | O64: Overhead pipe manifold connecting pump to brass nozzles.
A65: To Buy | B65: F6 | C65: 12V DC Solenoid Valve (1/2" NC) | D65: Actuators | E65: Direct-acting 12V DC valve, normally closed (NC), brass or nylon body. | F65: 1 | G65: pc | H65: 250 | I65: 450 | J65: =F65*H65 | K65: =F65*I65 | M65: Shopee / Lazada / Makerlab PH | N65: 12V DC electric solenoid valve 1/2 inch normally closed | O65: Primary water shutoff. Shuts closed if power fails.
A66: To Buy | B66: F7 | C66: Push-Fit Water Fittings (1/2" Male to 6mm) | D66: Actuators | E66: Food-grade POM push-fit adapter, 1/2" BSP thread to 1/4" (6mm) OD tube. | F66: 2 | G66: pcs | H66: 30 | I66: 60 | J66: =F66*H66 | K66: =F66*I66 | M66: Hardware Store / Shopee | N66: Quick connect fitting 1/2 male thread to 1/4 6mm tube | O66: Leak-free transition from solenoid/pump to PE misting tube.
A67: To Buy | B67: F8 | C67: 12V Full-Spectrum LED Grow Light Strip (1m) | D67: Actuators | E67: 12V SMD5050, 4:1 Red:Blue + White spectrum, IP65 waterproof silicone jacket. | F67: 1 | G67: strip | H67: 300 | I67: 800 | J67: =F67*H67 | K67: =F67*I67 | M67: Shopee / Lazada | N67: 12V full spectrum LED grow light strip waterproof IP65 | O67: Stimulates oyster mushroom pinhead & cap formation.
A68: To Buy | B68: F9 | C68: Water Reservoir Container (5-10 Liters) | D68: Actuators | E68: Heavy-duty translucent HDPE plastic container with tight lid & drain port. | F68: 1 | G68: pc | H68: 80 | I68: 200 | J68: =F68*H68 | K68: =F68*I68 | M68: Hardware Store / Grocery | N68: Plastic container with lid 10L translucent | O68: Dedicated clean water supply; holds capacitive level sensor.
A69: To Buy | B69: F10 | C69: PTFE Thread Seal Teflon Tape (1/2" × 10m) | D69: Actuators | E69: Standard density PTFE sealant tape for plumbing connections. | F69: 1 | G69: roll | H69: 25 | I69: 30 | J69: =F69*H69 | K69: =F69*I69 | M69: Any Hardware Store | N69: Teflon tape 1/2 inch | O69: Guarantees zero leaks on all threaded water joints.
A70: To Buy | B70: F11 | C70: Stainless Hose Clamps (10-16mm, SS304) | D70: Actuators | E70: 304 stainless steel band & screw, rustproof in 95% humidity. | F70: 4 | G70: pcs | H70: 10 | I70: 15 | J70: =F70*H70 | K70: =F70*I70 | M70: Hardware Store | N70: Stainless hose clamps 10-16mm | O70: Secures intake/discharge hoses to pump barbs under pressure.
A71: To Buy | B71: F12 | C71: 6mm Inline One-Way Check Valve | D71: Actuators | E71: Diaphragm non-return valve, cracking pressure 0.01 MPa, fits 6mm tube. | F71: 1 | G71: pc | H71: 40 | I71: 90 | J71: =F71*H71 | K71: =F71*I71 | M71: Shopee / Aquarium Store | N71: Inline one way check valve 6mm | O71: Prevents backflow and keeps pump head primed.
A72: Subtotal — Category F (Actuators): | J72: =SUM(J60:J71) | K72: =SUM(K60:K71) | L72: =SUM(L60:L71)
A73: 📦 CATEGORY G: ENCLOSURE & MOUNTING
A74: To Buy | B74: G1 | C74: IP65 ABS Waterproof Enclosure (255×200×80mm) | D74: Enclosure & Mounting | E74: Weatherproof ABS box with rubber silicone sealing gasket & brass inserts. | F74: 1 | G74: pc | H74: 300 | I74: 500 | J74: =F74*H74 | K74: =F74*I74 | M74: Shopee / Lazada / Hardware | N74: IP65 waterproof junction box ABS 255x200x80 | O74: Houses ESP32, PSU, relays, and terminal blocks safely.
A75: To Buy | B75: G2 | C75: 35mm DIN Rail (15cm) + Mounting Clips | D75: Enclosure & Mounting | E75: Standard slotted steel DIN rail 35mm + modular mounting clips & brackets. | F75: 1 | G75: set | H75: 60 | I75: 120 | J75: =F75*H75 | K75: =F75*I75 | M75: Shopee / Lazada | N75: DIN rail 35mm 15cm with mounting brackets | O75: Clean industrial mounting for terminal blocks and PSU.
A76: To Buy | B76: G3 | C76: M3 Nylon PCB Standoffs / Spacers Kit | D76: Enclosure & Mounting | E76: Assorted M3 nylon threaded pillars (6-20mm), nuts, and screws. | F76: 1 | G76: set | H76: 30 | I76: 50 | J76: =F76*H76 | K76: =F76*I76 | M76: Shopee / Electronics Store | N76: M3 nylon hex standoff assortment kit | O76: Mounts ESP32 board and perfboards elevated off base.
A77: To Buy | B77: G4 | C77: Wall-Mount Brackets + Screws (Stainless) | D77: Enclosure & Mounting | E77: 304 stainless steel L-brackets with masonry wall plugs & screws. | F77: 1 | G77: set | H77: 30 | I77: 60 | J77: =F77*H77 | K77: =F77*I77 | M77: Hardware Store | N77: Stainless steel mounting bracket with screws | O77: Secures controller cabinet firmly to mushroom house wall.
A78: To Buy | B78: G5 | C78: Rubber Wiring Grommets Assortment | D78: Enclosure & Mounting | E78: Weatherproof nitrile rubber grommets (10mm to 25mm). | F78: 1 | G78: pack | H78: 30 | I78: 50 | J78: =F78*H78 | K78: =F78*I78 | M78: Shopee / Hardware Store | N78: Rubber grommets assortment kit | O78: Protects wiring where cables pass through drilled holes.
A79: Subtotal — Category G (Enclosure & Mounting): | J79: =SUM(J74:J78) | K79: =SUM(K74:K78) | L79: =SUM(L74:L78)
A80: 🔧 CATEGORY H: MISCELLANEOUS, TOOLS & FABRICATION CONSUMABLES
A81: To Buy | B81: H1 | C81: USB-C Data & Sync Cable (1.0m, Fast Sync) | D81: Miscellaneous, Tools & Fabrication Consumables | E81: 28/24 AWG shielded copper cable supporting high-speed serial data (not charge-only). | F81: 1 | G81: pc | H81: 50 | I81: 100 | J81: =F81*H81 | K81: =F81*I81 | M81: Shopee / Phone Accessories Store | N81: USB-C data cable 1m high speed | O81: Required for flashing firmware and Serial Monitor logs.
A82: To Buy | B82: H2 | C82: 4–20mm Titanium HSS Step Drill Bit | D82: Miscellaneous, Tools & Fabrication Consumables | E82: High-speed steel conical step bit with 9 increment steps (4-20mm). | F82: 1 | G82: pc | H82: 100 | I82: 200 | J82: =F82*H82 | K82: =F82*I82 | M82: Shopee / Hardware Store | N82: Step drill bit 4-20mm titanium HSS | O82: Cuts clean 16mm holes for GX16 sockets, glands & switches.
A83: To Buy | B83: H3 | C83: Electrical Tape (3M Scotch or equivalent) | D83: Miscellaneous, Tools & Fabrication Consumables | E83: Heavy-duty vinyl electrical insulating tape, flame retardant. | F83: 2 | G83: rolls | H83: 25 | I83: 40 | J83: =F83*H83 | K83: =F83*I83 | M83: Any Hardware Store | N83: 3M electrical tape original black | O83: General wire insulation, color identification, and bundling.
A84: To Buy | B84: H4 | C84: 3M VHB Double-Sided Foam Tape (12mm × 3m) | D84: Miscellaneous, Tools & Fabrication Consumables | E84: High-strength acrylic foam bonding tape, extreme moisture resistance. | F84: 1 | G84: roll | H84: 40 | I84: 80 | J84: =F84*H84 | K84: =F84*I84 | M84: Shopee / Hardware Store | N84: 3M VHB double sided tape heavy duty | O84: Mounts OLED display and indicator bezels to cabinet face.
A85: To Buy | B85: H5 | C85: Clear Weatherproof Silicone Sealant (100ml) | D85: Miscellaneous, Tools & Fabrication Consumables | E85: 100% RTV silicone sealant, mold-resistant, flexible waterproof seal. | F85: 1 | G85: tube | H85: 80 | I85: 120 | J85: =F85*H85 | K85: =F85*I85 | M85: Any Hardware Store | N85: Clear silicone sealant RTV waterproof | O85: Seals perimeter of all cutouts to keep enclosure IP65.
A86: To Buy | B86: H6 | C86: Printable Weatherproof Vinyl Label Sheets | D86: Miscellaneous, Tools & Fabrication Consumables | E86: Waterproof adhesive vinyl sticker paper for labeling ports & switches. | F86: 1 | G86: set | H86: 30 | I86: 50 | J86: =F86*H86 | K86: =F86*I86 | M86: Shopee / Print Shop | N86: Waterproof label sticker paper A4 vinyl | O86: Clear labeling: [MAINS], [EXHAUST], [MISTER], [LIGHT], [PROBE].
A87: To Buy | B87: H7 | C87: 40W Soldering Iron with Stand & Sponge | D87: Miscellaneous, Tools & Fabrication Consumables | E87: 220V 40W pencil iron with fine tip, wire stand & cleaning sponge. | F87: 1 | G87: pc | H87: 0 | I87: 350 | J87: =F87*H87 | K87: =F87*I87 | M87: Shopee / Hardware Store (0 if owned) | N87: Soldering iron 40W with stand | O87: Essential for perfboard, diodes, and GX16 connectors.
A88: Subtotal — Category H (Miscellaneous, Tools & Fabrication Consumables): | J88: =SUM(J81:J87) | K88: =SUM(K81:K87) | L88: =SUM(L81:L87)
A90: ★ GRAND TOTAL (ALL 68 COMPONENTS): | J90: =J13+J23+J37+J46+J58+J72+J79+J88 | K90: =K13+K23+K37+K46+K58+K72+K79+K88 | L90: =L13+L23+L37+L46+L58+L72+L79+L88

Sheet 📊 Executive Summary
A1: 🍄 KABUTECH HIYAS — EXECUTIVE BUDGET & PROCUREMENT DASHBOARD
A2: Live Project Financial Overview, Category Allocations & Status Tracking
A4: TOTAL ALLOCATED BUDGET | C4: EST. MIN TOTAL | D4: EST. MAX TOTAL | E4: ACTUAL SPENT | F4: BUDGET REMAINING | G4: TOTAL ITEMS
A5: 15000 | C5: ='📋 Materials Checklist'!J90 | D5: ='📋 Materials Checklist'!K90 | E5: ='📋 Materials Checklist'!L90 | F5: =A5-E5 | G5: 68
A6: Fixed Project Ceiling | C6: Smart Shopee / Lazada | D6: Worst-case retail buffer | E6: Tracked from purchases | F6: Surplus / Buffer | G6: Across 8 Categories
A8: 📊 CATEGORY BUDGET BREAKDOWN & SPENDING SUMMARY
A9: Cat Code | B9: Category Description | C9: Items Count | D9: Est. Min (₱) | E9: Est. Max (₱) | F9: Actual Spent (₱) | G9: % of Budget (Max)
A10: Category A | B10: Sensors & Probe Electronics (Quality-Grade) | C10: 7 | D10: ='📋 Materials Checklist'!J13 | E10: ='📋 Materials Checklist'!K13 | F10: ='📋 Materials Checklist'!L13 | G10: =E10/$A$5
A11: Category B | B11: Hanging Sensor Probe Housing (PVC Bell Reducer Design) | C11: 8 | D11: ='📋 Materials Checklist'!J23 | E11: ='📋 Materials Checklist'!K23 | F11: ='📋 Materials Checklist'!L23 | G11: =E11/$A$5
A12: Category C | B12: Controller Board & Core Electronics | C12: 12 | D12: ='📋 Materials Checklist'!J37 | E12: ='📋 Materials Checklist'!K37 | F12: ='📋 Materials Checklist'!L37 | G12: =E12/$A$5
A13: Category D | B13: Power Supply & Distribution | C13: 7 | D13: ='📋 Materials Checklist'!J46 | E13: ='📋 Materials Checklist'!K46 | F13: ='📋 Materials Checklist'!L46 | G13: =E13/$A$5
A14: Category E | B14: Connectors & Wiring | C14: 10 | D14: ='📋 Materials Checklist'!J58 | E14: ='📋 Materials Checklist'!K58 | F14: ='📋 Materials Checklist'!L58 | G14: =E14/$A$5
A15: Category F | B15: Actuators (The Things Being Controlled) | C15: 12 | D15: ='📋 Materials Checklist'!J72 | E15: ='📋 Materials Checklist'!K72 | F15: ='📋 Materials Checklist'!L72 | G15: =E15/$A$5
A16: Category G | B16: Enclosure & Mounting | C16: 5 | D16: ='📋 Materials Checklist'!J79 | E16: ='📋 Materials Checklist'!K79 | F16: ='📋 Materials Checklist'!L79 | G16: =E16/$A$5
A17: Category H | B17: Miscellaneous, Tools & Fabrication Consumables | C17: 7 | D17: ='📋 Materials Checklist'!J88 | E17: ='📋 Materials Checklist'!K88 | F17: ='📋 Materials Checklist'!L88 | G17: =E17/$A$5
A18: TOTALS | B18: All 8 System Categories Combined | C18: =SUM(C10:C17) | D18: =SUM(D10:D17) | E18: =SUM(E10:E17) | F18: =SUM(F10:F17) | G18: =SUM(G10:G17)
A20: 💡 BUDGET ANALYSIS & KEY TAKEAWAYS:
A21: 1. Best-Case Budget Target: | B21: ₱9,770 — Achievable by taking advantage of Shopee/Lazada monthly sales (e.g., Payday, 10.10, 11.11), platform vouchers, and free shipping coins.
A22: 2. Realistic Budget Target: | B22: ₱12,000–₱13,500 — Leaves a healthy buffer of ₱1,500–₱3,000 within your ₱15,000 cap for unexpected spares, extra wire, or shipping fees.
A23: 3. High-End Worst-Case: | B23: ₱15,550 — Even if buying every single item at peak retail with zero discounts and buying a brand new soldering iron, it sits right at your ₱15k ceiling.
A24: 4. Key Cost Driver: | B24: The SCD41 True NDIR CO₂ Sensor (₱1,800–₱2,500) represents ~18% of total expenditure. It is the single most critical investment for your thesis credibility.

Sheet 🛒 Vendor & Shopping Guide
A1: 🍄 KABUTECH HIYAS — PHILIPPINE SOURCING & PROCUREMENT GUIDE
A2: Recommended Local Vendors, Shopping Batches & Quality Verification Checks
A4: 🏪 RECOMMENDED STORES IN THE PHILIPPINES
A5: Store / Vendor | B5: Platform / Location | C5: Items to Source Here | D5: Pros / Recommendations | E5: Est. Delivery
A6: Makerlab Electronics | B6: Shopee Mall / Lazada / QC Physical | C6: ESP32-S3, Relays, OLED, SHT31, Level Shifter, XKC-Y25 | D6: Fast NCR delivery (1-2 days), tested genuine boards | E6: 1–2 days
A7: CircuitRocks Philippines | B7: Shopee / Website / Mandaluyong | C7: BH1750, SHT31-D, Prototyping PCBs, Connectors | D7: High quality verified sensors, technical support | E7: 1–3 days
A8: e-Gizmo Mechatronix | B8: Taft Ave Manila / Online Store | C8: Sensors, Relays, Breadboards, Headers, Power components | D8: Long-running local supplier, student thesis friendly | E8: 1–3 days
A9: Alexan Commercial | B9: Raon Quiapo / SM Megamall / Online | C9: 12V Switching PSU, IEC C14 Inlets, Switches, Diodes, Fuses | D9: Best for industrial power supplies, enclosure accessories | E9: Same day / 2 days
A10: Shopee Overseas (China) | B10: Shopee App (Search keyword) | C10: SCD41 NDIR CO2 Sensor, GX16 Connectors, Misting Nozzles | D10: 30-50% cheaper on SCD41 and aviation plugs | E10: 5–8 days
A11: Wilcon Depot / Citi Hardware | B11: Local Physical Branches Nationwide | C11: PVC Bell Reducer, Teflon Tape, Hose Clamps, Wall Brackets | D11: Heavy-duty sanitary grade PVC fittings, inspect in-person | E11: Immediate
A12: Ace Hardware / Handyman | B12: Malls Nationwide | C12: Electrical tape, 3M VHB tape, Silicone sealant, Zip ties | D12: Branded adhesives & sealants (3M, Pioneer, Devcon) | E12: Immediate
A14: 📅 RECOMMENDED 4-PHASE ORDERING ROADMAP
A15: Phase | B15: Target Milestone | C15: Items to Order | D15: Purpose & Validation Goal | E15: Est. Spend
A16: Phase 1 | B16: Core Sensors & Logic Bench Test | C16: ESP32-S3, SHT31, BH1750, SCD41, OLED, Jumpers, Breadboard | D16: Bench-test sensor polling, I2C bus scan, and Firebase telemetry transmission. | E16: ₱2,800 – ₱3,600
A17: Phase 2 | B17: Power & Actuator Control Bench Test | C17: 12V PSU, 8-Ch Relay, Logic Shifter, Fans, Misting Pump, Solenoid Valve | D17: Validate relay switching, flyback diodes, and actuator trigger responsiveness. | E17: ₱3,500 – ₱4,800
A18: Phase 3 | B18: Probe & Enclosure Fabrication | C18: IP65 Box, PVC Bell Reducer, Cable Glands, GX16 Plugs, Step Drill Bit, Sealant | D18: Drill enclosure, solder aviation connectors, fabricate waterproof hanging probe. | E18: ₱1,800 – ₱2,600
A19: Phase 4 | B19: Plumbing & Final Deployment | C19: Misting Tubing, Brass Nozzles, Check Valve, Reservoir, Wall Brackets | D19: Assemble plumbing manifold in grow house, calibrate sensors, end-to-end PID test. | E19: ₱1,200 – ₱2,000
A21: 🔍 QUALITY VERIFICATION CHECKLIST (BEFORE YOU BUY)
A22: ESP32-S3 Flash/PSRAM | B22: Ensure listing states 'N16R8' (16MB Flash / 8MB PSRAM). Generic N4 (4MB) has insufficient memory for dual-core FreeRTOS, Firebase queue, and web stack simultaneously.
A23: SCD41 vs SCD30 / MQ-135 | B23: Do NOT accept MQ-135 or CCS811. Only Sensirion SCD40 or SCD41 offers photoacoustic true NDIR CO2 measurement. Look for Sensirion laser-etched metal package.
A24: SHT31 vs DHT11 / DHT22 | B24: DHT11 will fail rapidly at >85% RH in a mushroom house. The Sensirion SHT31-D features an integrated heater and internal humidity polymer rated for 0-100% RH.
A25: Aviation Connectors (GX16) | B25: Order matching Male + Female pairs (GX16-4). 4-pin is standard: Pin 1 = 12V/VCC, Pin 2 = GND, Pin 3 = Signal/SDA, Pin 4 = SCL/Trigger.
A26: Power Supply Quality | B26: Verify the 12V 5A PSU has an aluminum casing with ventilation slots and a trimmer pot to fine-tune 12.0VDC. Avoid unbranded lightweight plastic wall-warts for continuous 24/7 duty.
